[{"id":692,"Address":"rue inconnu 0","city":"Ville0","postalCode":36174,"mainAddress":true,"dwellingType":"Appartement","dwellingSize":146,"rental":true,"service":[{"id":1159,"name":"Assurance-habitation","link":"https:\/\/www.Assurance-habitation.fr","priceMonth":687,"priceYear":8244,"type":"Assurance-habitation"},{"id":1163,"name":"Autre","link":"https:\/\/www.Autre.fr","priceMonth":59,"priceYear":708,"type":"Autre"},{"id":1171,"name":"Assurance-habitation","link":"https:\/\/www.Assurance-habitation.fr","priceMonth":21,"priceYear":252,"type":"Assurance-habitation"},{"id":1172,"name":"Eau","link":"https:\/\/www.Eau.fr","priceMonth":32,"priceYear":384,"type":"Eau"}],"number":43,"additional":null,"rentprice":null,"RealEstateAgency":null}]