[{"id":686,"name":"Loyer","link":"citya","priceMonth":120,"priceYear":1440,"type":"Loyer","userAddress":{"id":468,"Address":"R\u00e9sidence Caudalie b\u00e2timent A","city":"BORDEAUX","postalCode":33140,"mainAddress":false,"dwellingType":"Appartement","dwellingSize":100,"rental":true}},{"id":687,"name":"assurance habitation","link":"https:\/\/www.Eau.fr","priceMonth":120,"priceYear":1440,"type":"\u00c9lectricit\u00e9","userAddress":{"id":468,"Address":"R\u00e9sidence Caudalie b\u00e2timent A","city":"BORDEAUX","postalCode":33140,"mainAddress":false,"dwellingType":"Appartement","dwellingSize":100,"rental":true}}]